buse/__init__.py
buse/main.py
buse/mcp_server.py
buse/models.py
buse/session.py
buse/utils.py
buse/vision.py
buse-0.4.1.dist-info/METADATA
buse-0.4.1.dist-info/WHEEL
buse-0.4.1.dist-info/entry_points.txt
buse-0.4.1.dist-info/licenses/LICENSE
buse-0.4.1.dist-info/RECORD
