Metadata-Version: 2.4
Name: buse
Version: 0.4.1
Summary: buse: Stateless CLI for browser-use
Project-URL: Homepage, https://github.com/rinvii/buse
Project-URL: Repository, https://github.com/rinvii/buse
Project-URL: Issues, https://github.com/rinvii/buse/issues
Author: rinvii
License: MIT License
License-File: LICENSE
Keywords: agents,automation,browser,browser-use,cli
Classifier: Development Status :: 3 - Alpha
Classifier: License :: OSI Approved :: MIT License
Classifier: Programming Language :: Python :: 3
Classifier: Programming Language :: Python :: 3.12
Classifier: Topic :: Internet :: WWW/HTTP :: Browsers
Classifier: Topic :: Software Development :: Testing
Requires-Python: >=3.12
Requires-Dist: anthropic>=0.75.0
Requires-Dist: browser-use>=0.11.2
Requires-Dist: httpx>=0.28.1
Requires-Dist: mcp>=1.25.0
Requires-Dist: pillow>=10.0.0
Requires-Dist: psutil>=7.2.1
Requires-Dist: pydantic>=2.12.5
Requires-Dist: rich>=14.2.0
Requires-Dist: toon-format>=0.9.0b1
Requires-Dist: typer>=0.21.1
Provides-Extra: test
Requires-Dist: pytest-asyncio>=0.23.0; extra == 'test'
Requires-Dist: pytest-cov>=5.0.0; extra == 'test'
Requires-Dist: pytest>=8.0.0; extra == 'test'
